tests/__init__.py
tests/test_timer.py
ttimer/__init__.py
ttimer/timer.py
ttimer-0.0.2.dist-info/LICENSE
ttimer-0.0.2.dist-info/METADATA
ttimer-0.0.2.dist-info/WHEEL
ttimer-0.0.2.dist-info/top_level.txt
ttimer-0.0.2.dist-info/RECORD
