Metadata-Version: 2.1
Name: ttimer
Version: 0.0.2
Summary: ttimer - tree timer
Home-page: https://github.com/nyanp/ttimer
Author: nyanp
Author-email: Noumi.Taiga@gmail.com
License: MIT
Keywords: timer profiler
Platform: UNKNOWN
Classifier: License :: OSI Approved :: MIT License
Classifier: Programming Language :: Python :: 3.7
Classifier: Programming Language :: Python :: 3.8
Classifier: Programming Language :: Python :: 3.9
Classifier: Programming Language :: Python :: 3.10
License-File: LICENSE
Requires-Dist: anytree
Requires-Dist: tabulate
